CHANGES.md
CONTRIBUTING.md
LICENSE.md
MANIFEST.in
README.rst
read_the_docs.txt
requirements.txt
setup.py
bin/README.md
bin/dataduct
dataduct/__init__.py
dataduct/config/__init__.py
dataduct/config/config.py
dataduct/config/config_actions.py
dataduct/config/constants.py
dataduct/config/credentials.py
dataduct/config/logger_config.py
dataduct/data_access/__init__.py
dataduct/data_access/connection.py
dataduct/data_access/open_shell.py
dataduct/database/__init__.py
dataduct/database/column.py
dataduct/database/database.py
dataduct/database/history_table.py
dataduct/database/relation.py
dataduct/database/select_statement.py
dataduct/database/table.py
dataduct/database/view.py
dataduct/database/parsers/__init__.py
dataduct/database/parsers/create_table.py
dataduct/database/parsers/create_view.py
dataduct/database/parsers/helpers.py
dataduct/database/parsers/select_query.py
dataduct/database/parsers/transform.py
dataduct/database/parsers/utils.py
dataduct/database/sql/__init__.py
dataduct/database/sql/sql_script.py
dataduct/database/sql/sql_statement.py
dataduct/database/sql/transaction.py
dataduct/database/sql/utils.py
dataduct/etl/__init__.py
dataduct/etl/etl_actions.py
dataduct/etl/etl_pipeline.py
dataduct/etl/utils.py
dataduct/pipeline/__init__.py
dataduct/pipeline/activity.py
dataduct/pipeline/copy_activity.py
dataduct/pipeline/data_pipeline.py
dataduct/pipeline/default_object.py
dataduct/pipeline/ec2_resource.py
dataduct/pipeline/emr_activity.py
dataduct/pipeline/emr_resource.py
dataduct/pipeline/mysql_node.py
dataduct/pipeline/pipeline_object.py
dataduct/pipeline/precondition.py
dataduct/pipeline/redshift_copy_activity.py
dataduct/pipeline/redshift_database.py
dataduct/pipeline/redshift_node.py
dataduct/pipeline/s3_node.py
dataduct/pipeline/schedule.py
dataduct/pipeline/shell_command_activity.py
dataduct/pipeline/sns_alarm.py
dataduct/pipeline/sql_activity.py
dataduct/pipeline/utils.py
dataduct/qa/__init__.py
dataduct/qa/check.py
dataduct/qa/column_check.py
dataduct_flywire.egg-info/PKG-INFO
dataduct_flywire.egg-info/SOURCES.txt
dataduct_flywire.egg-info/dependency_links.txt
dataduct_flywire.egg-info/namespace_packages.txt
dataduct_flywire.egg-info/requires.txt
dataduct_flywire.egg-info/top_level.txt